pymapr_kafkarest/__init__.py
pymapr_kafkarest/exceptions.py
pymapr_kafkarest/kafkarest.py
pymapr_kafkarest-0.1.1.dist-info/METADATA
pymapr_kafkarest-0.1.1.dist-info/WHEEL
pymapr_kafkarest-0.1.1.dist-info/top_level.txt
pymapr_kafkarest-0.1.1.dist-info/RECORD
